fnirsLink/__init__.py
fnirsLink/__version__.py
fnirsLink/connection.py
fnirsLink/exception.py
fnirsLink/fnirs_link.py
fnirsLink/get_server_data.py
fnirsLink/response.py
fnirsLink/socket_server.py
fnirsLink/sys_version.py
fnirsLink/url_name.py
fnirsLink/web_request.py
fnirslink-0.0.7.dist-info/LICENSE
fnirslink-0.0.7.dist-info/METADATA
fnirslink-0.0.7.dist-info/WHEEL
fnirslink-0.0.7.dist-info/top_level.txt
fnirslink-0.0.7.dist-info/RECORD
