Metadata-Version: 2.1
Name: fnirslink
Version: 0.0.7
Summary: 近红外连接库python版本.
Home-page: http://www.znion.com
Author: Mao Run
Author-email: maorun@znion.com
License: MIT
Platform: UNKNOWN
Classifier: License :: OSI Approved :: MIT License
Classifier: Programming Language :: Python
Classifier: Programming Language :: Python :: 3
Classifier: Programming Language :: Python :: 3.6
Classifier: Programming Language :: Python :: Implementation :: CPython
Classifier: Programming Language :: Python :: Implementation :: PyPy
Requires-Python: >=3.7.0
Requires-Dist: requests
Requires-Dist: urllib3
